{
    "Ar36": {
        "error": 0.00019402924259786847,
        "error_type": "SEM",
        "filter_outliers_dict": {
            "filter_outliers": true,
            "iterations": 1,
            "std_devs": 3,
            "use_iqr_filtering": false,
            "use_standard_deviation_filtering": false
        },
        "fit": "Parabolic",
        "fn": 338,
        "include_baseline_error": false,
        "n": 340,
        "outlier_excluded": [
            314,
            335
        ],
        "reviewed": true,
        "user_excluded": [],
        "value": 0.001935560125205741
    },
    "Ar37": {
        "error": 0.01736212728030421,
        "error_type": "SEM",
        "filter_outliers_dict": {
            "filter_outliers": true,
            "iterations": 1,
            "std_devs": 3,
            "use_iqr_filtering": false,
            "use_standard_deviation_filtering": false
        },
        "fit": "Linear",
        "fn": 340,
        "include_baseline_error": false,
        "n": 340,
        "outlier_excluded": [],
        "reviewed": true,
        "user_excluded": [],
        "value": 0.06133813735670178
    },
    "Ar38": {
        "error": 0.005911259202618918,
        "error_type": "SEM",
        "filter_outliers_dict": {
            "filter_outliers": true,
            "iterations": 1,
            "std_devs": 3,
            "use_iqr_filtering": false,
            "use_standard_deviation_filtering": false
        },
        "fit": "Linear",
        "fn": 340,
        "include_baseline_error": false,
        "n": 340,
        "outlier_excluded": [],
        "reviewed": true,
        "user_excluded": [],
        "value": 0.09045427993534885
    },
    "Ar39": {
        "error": 0.015737212676560523,
        "error_type": "SEM",
        "filter_outliers_dict": {
            "filter_outliers": true,
            "iterations": 1,
            "std_devs": 3,
            "use_iqr_filtering": false,
            "use_standard_deviation_filtering": false
        },
        "fit": "Parabolic",
        "fn": 338,
        "include_baseline_error": false,
        "n": 340,
        "outlier_excluded": [
            208,
            283
        ],
        "reviewed": true,
        "user_excluded": [],
        "value": -0.013413828597005236
    },
    "Ar40": {
        "error": 0.03238020447479409,
        "error_type": "SEM",
        "filter_outliers_dict": {
            "filter_outliers": true,
            "iterations": 1,
            "std_devs": 3,
            "use_iqr_filtering": false,
            "use_standard_deviation_filtering": false
        },
        "fit": "Parabolic",
        "fn": 339,
        "include_baseline_error": false,
        "n": 340,
        "outlier_excluded": [
            319
        ],
        "reviewed": true,
        "user_excluded": [],
        "value": -0.5573482090410055
    }
}