{
    "Ar36": {
        "error": 0.0001396740172515337,
        "error_type": "",
        "fit": "previous",
        "references": [
            {
                "exclude": false,
                "record_id": "bc-03-F-180"
            }
        ],
        "value": 0.002056812421306703
    },
    "Ar37": {
        "error": 0.01400889676437957,
        "error_type": "",
        "fit": "previous",
        "references": [
            {
                "exclude": false,
                "record_id": "bc-03-F-180"
            }
        ],
        "value": 0.054089454986408166
    },
    "Ar38": {
        "error": 0.004889488051611016,
        "error_type": "",
        "fit": "previous",
        "references": [
            {
                "exclude": false,
                "record_id": "bc-03-F-180"
            }
        ],
        "value": 0.005932611388666256
    },
    "Ar39": {
        "error": 0.013308514926531472,
        "error_type": "",
        "fit": "previous",
        "references": [
            {
                "exclude": false,
                "record_id": "bc-03-F-180"
            }
        ],
        "value": 0.02173788497928084
    },
    "Ar40": {
        "error": 0.027699968495388718,
        "error_type": "",
        "fit": "previous",
        "references": [
            {
                "exclude": false,
                "record_id": "bc-03-F-180"
            }
        ],
        "value": 0.13072484355320224
    }
}